{
    "values": [
        {"index": 0, "anomaly": 0, "trip_risk": 1, "status": "Operating Within Thresholds", "dodgy_sensors": []},
        {"index": 1, "anomaly": 0, "trip_risk": 1, "status": "Operating Within Thresholds", "dodgy_sensors": []},
        {"index": 2, "anomaly": 0, "trip_risk": 2, "status": "Operating Within Thresholds", "dodgy_sensors": []},
        {"index": 3, "anomaly": 0, "trip_risk": 1, "status": "Operating Within Thresholds", "dodgy_sensors": []},
        {"index": 4, "anomaly": 0, "trip_risk": 2, "status": "Operating Within Thresholds", "dodgy_sensors": []},
        {"index": 5, "anomaly": 0, "trip_risk": 2, "status": "Operating Within Thresholds", "dodgy_sensors": []},
        {"index": 6, "anomaly": 0, "trip_risk": 2, "status": "Operating Within Thresholds", "dodgy_sensors": []},
        {"index": 7, "anomaly": 0, "trip_risk": 1, "status": "Operating Within Thresholds", "dodgy_sensors": []},
        {"index": 8, "anomaly": 0, "trip_risk": 2, "status": "Operating Within Thresholds", "dodgy_sensors": []},
        {"index": 9, "anomaly": 0, "trip_risk": 1, "status": "Operating Within Thresholds", "dodgy_sensors": []},
        {"index": 10, "anomaly": 0, "trip_risk": 2, "status": "Operating Within Thresholds", "dodgy_sensors": []},
        {"index": 11, "anomaly": 0, "trip_risk": 3, "status": "Operating Within Thresholds", "dodgy_sensors": []},
        {"index": 12, "anomaly": 0, "trip_risk": 2, "status": "Operating Within Thresholds", "dodgy_sensors": []},
        {"index": 13, "anomaly": 0, "trip_risk": 1, "status": "Operating Within Thresholds", "dodgy_sensors": []},
        {"index": 14, "anomaly": 0, "trip_risk": 2, "status": "Operating Within Thresholds", "dodgy_sensors": []},
        {"index": 15, "anomaly": 0, "trip_risk": 2, "status": "Operating Within Thresholds", "dodgy_sensors": []},
        {"index": 16, "anomaly": 0, "trip_risk": 2, "status": "Operating Within Thresholds", "dodgy_sensors": []},
        {"index": 17, "anomaly": 0, "trip_risk": 1, "status": "Operating Within Thresholds", "dodgy_sensors": []},
        {"index": 18, "anomaly": 0, "trip_risk": 2, "status": "Operating Within Thresholds", "dodgy_sensors": []},
        {"index": 19, "anomaly": 0, "trip_risk": 2, "status": "Operating Within Thresholds", "dodgy_sensors": []},
        {"index": 20, "anomaly": 0, "trip_risk": 1, "status": "Operating Within Thresholds", "dodgy_sensors": []},
        {"index": 21, "anomaly": 0, "trip_risk": 1, "status": "Operating Within Thresholds", "dodgy_sensors": []},
        {"index": 22, "anomaly": 0, "trip_risk": 2, "status": "Operating Within Thresholds", "dodgy_sensors": []},
        {"index": 23, "anomaly": 0, "trip_risk": 1, "status": "Operating Within Thresholds", "dodgy_sensors": []},
        {"index": 24, "anomaly": 0, "trip_risk": 1, "status": "Operating Within Thresholds", "dodgy_sensors": []},
        {"index": 25, "anomaly": 0, "trip_risk": 2, "status": "Operating Within Thresholds", "dodgy_sensors": []},
        {"index": 26, "anomaly": 0, "trip_risk": 1, "status": "Operating Within Thresholds", "dodgy_sensors": []},
        {"index": 27, "anomaly": 0, "trip_risk": 2, "status": "Operating Within Thresholds", "dodgy_sensors": []},
        {"index": 28, "anomaly": 0, "trip_risk": 2, "status": "Operating Within Thresholds", "dodgy_sensors": []},
        {"index": 29, "anomaly": 0, "trip_risk": 2, "status": "Operating Within Thresholds", "dodgy_sensors": []},
        {"index": 30, "anomaly": 0, "trip_risk": 3, "status": "Operating Within Thresholds", "dodgy_sensors": []},
        {"index": 31, "anomaly": 0, "trip_risk": 4, "status": "Operating Within Thresholds", "dodgy_sensors": []},
        {"index": 32, "anomaly": 0, "trip_risk": 2, "status": "Operating Within Thresholds", "dodgy_sensors": []},
        {"index": 33, "anomaly": 0, "trip_risk": 1, "status": "Operating Within Thresholds", "dodgy_sensors": []},
        {"index": 34, "anomaly": 0, "trip_risk": 1, "status": "Operating Within Thresholds", "dodgy_sensors": []},
        {"index": 35, "anomaly": 0, "trip_risk": 2, "status": "Operating Within Thresholds", "dodgy_sensors": []},
        {"index": 36, "anomaly": 0, "trip_risk": 1, "status": "Operating Within Thresholds", "dodgy_sensors": []},
        {"index": 37, "anomaly": 0, "trip_risk": 2, "status": "Operating Within Thresholds", "dodgy_sensors": []},
        {"index": 38, "anomaly": 0, "trip_risk": 2, "status": "Operating Within Thresholds", "dodgy_sensors": []},
        {"index": 39, "anomaly": 0, "trip_risk": 2, "status": "Operating Within Thresholds", "dodgy_sensors": []},
        {"index": 40, "anomaly": 0, "trip_risk": 1, "status": "Operating Within Thresholds", "dodgy_sensors": []},
        {"index": 41, "anomaly": 0, "trip_risk": 1, "status": "Operating Within Thresholds", "dodgy_sensors": []},
        {"index": 42, "anomaly": 0, "trip_risk": 2, "status": "Operating Within Thresholds", "dodgy_sensors": []},
        {"index": 43, "anomaly": 0, "trip_risk": 3, "status": "Operating Within Thresholds", "dodgy_sensors": []},
        {"index": 44, "anomaly": 0, "trip_risk": 4, "status": "Operating Within Thresholds", "dodgy_sensors": []},
        {"index": 45, "anomaly": 0, "trip_risk": 4, "status": "Operating Within Thresholds", "dodgy_sensors": []},
        {"index": 46, "anomaly": 0, "trip_risk": 3, "status": "Operating Within Thresholds", "dodgy_sensors": []},
        {"index": 47, "anomaly": 0, "trip_risk": 5, "status": "Operating Within Thresholds", "dodgy_sensors": []},
        {"index": 48, "anomaly": 0, "trip_risk": 3, "status": "Operating Within Thresholds", "dodgy_sensors": []},
        {"index": 49, "anomaly": 0, "trip_risk": 3, "status": "Operating Within Thresholds", "dodgy_sensors": []},
        {"index": 50, "anomaly": 0, "trip_risk": 2, "status": "Operating Within Thresholds", "dodgy_sensors": []},
        {"index": 51, "anomaly": 0, "trip_risk": 4, "status": "Operating Within Thresholds", "dodgy_sensors": []},
        {"index": 52, "anomaly": 0, "trip_risk": 2, "status": "Operating Within Thresholds", "dodgy_sensors": []},
        {"index": 53, "anomaly": 0, "trip_risk": 3, "status": "Operating Within Thresholds", "dodgy_sensors": []},
        {"index": 54, "anomaly": 0, "trip_risk": 4, "status": "Operating Within Thresholds", "dodgy_sensors": []},
        {"index": 55, "anomaly": 0, "trip_risk": 6, "status": "Operating Within Thresholds", "dodgy_sensors": []},
        {"index": 56, "anomaly": 0, "trip_risk": 5, "status": "Operating Within Thresholds", "dodgy_sensors": []},
        {"index": 57, "anomaly": 0, "trip_risk": 6, "status": "Operating Within Thresholds", "dodgy_sensors": []},
        {"index": 58, "anomaly": 0, "trip_risk": 4, "status": "Operating Within Thresholds", "dodgy_sensors": []},
        {"index": 59, "anomaly": 0, "trip_risk": 5, "status": "Operating Within Thresholds", "dodgy_sensors": []},
        {"index": 60, "anomaly": 0, "trip_risk": 6, "status": "Operating Within Thresholds", "dodgy_sensors": []},
        {"index": 61, "anomaly": 0, "trip_risk": 4, "status": "Operating Within Thresholds", "dodgy_sensors": []},
        {"index": 62, "anomaly": 0, "trip_risk": 6, "status": "Operating Within Thresholds", "dodgy_sensors": []},
        {"index": 63, "anomaly": 0, "trip_risk": 7, "status": "Operating Within Thresholds", "dodgy_sensors": []},
        {"index": 64, "anomaly": 0, "trip_risk": 7, "status": "Operating Within Thresholds", "dodgy_sensors": []},
        {"index": 65, "anomaly": 0, "trip_risk": 5, "status": "Operating Within Thresholds", "dodgy_sensors": []},
        {"index": 66, "anomaly": 0, "trip_risk": 6, "status": "Operating Within Thresholds", "dodgy_sensors": []},
        {"index": 67, "anomaly": 0, "trip_risk": 5, "status": "Operating Within Thresholds", "dodgy_sensors": []},
        {"index": 68, "anomaly": 0, "trip_risk": 8, "status": "Operating Within Thresholds", "dodgy_sensors": []},
        {"index": 69, "anomaly": 0, "trip_risk": 8, "status": "Operating Within Thresholds", "dodgy_sensors": []},
        {"index": 70, "anomaly": 0, "trip_risk": 12, "status": "LPC Warning", "dodgy_sensors": [{"A1": 50}, {"A2": 60}, {"P1": 23}]},
        {"index": 71, "anomaly": 0, "trip_risk": 10, "status": "LPC Warning", "dodgy_sensors": [{"A1": 63}, {"A2": 43}, {"P1": 54}]},
        {"index": 72, "anomaly": 0, "trip_risk": 16, "status": "LPC Warning", "dodgy_sensors": [{"A1": 56}, {"A2": 75}, {"P1": 24}]},
        {"index": 73, "anomaly": 0, "trip_risk": 14, "status": "LPC Warning", "dodgy_sensors": [{"A1": 21}, {"A2": 37}, {"P1": 45}]},
        {"index": 74, "anomaly": 0, "trip_risk": 15, "status": "LPC Warning", "dodgy_sensors": [{"A1": 47}, {"A2": 63}, {"P1": 25}]},
        {"index": 75, "anomaly": 0, "trip_risk": 16, "status": "LPC Warning", "dodgy_sensors": [{"A1": 74}, {"A2": 42}, {"P1": 16}]},
        {"index": 76, "anomaly": 1, "trip_risk": 23, "status": "LPC Warning", "dodgy_sensors": [{"A1": 35}, {"A2": 12}, {"P1": 34}]},
        {"index": 77, "anomaly": 0, "trip_risk": 4, "status": "Operating Within Thresholds", "dodgy_sensors": []},
        {"index": 78, "anomaly": 0, "trip_risk": 3, "status": "Operating Within Thresholds", "dodgy_sensors": []},
        {"index": 79, "anomaly": 0, "trip_risk": 2, "status": "Operating Within Thresholds", "dodgy_sensors": []},
        {"index": 80, "anomaly": 0, "trip_risk": 2, "status": "Operating Within Thresholds", "dodgy_sensors": []},
        {"index": 81, "anomaly": 0, "trip_risk": 3, "status": "Operating Within Thresholds", "dodgy_sensors": []},
        {"index": 82, "anomaly": 0, "trip_risk": 1, "status": "Operating Within Thresholds", "dodgy_sensors": []},
        {"index": 83, "anomaly": 0, "trip_risk": 2, "status": "Operating Within Thresholds", "dodgy_sensors": []},
        {"index": 84, "anomaly": 0, "trip_risk": 1, "status": "Operating Within Thresholds", "dodgy_sensors": []},
        {"index": 85, "anomaly": 0, "trip_risk": 2, "status": "Operating Within Thresholds", "dodgy_sensors": []},
        {"index": 86, "anomaly": 0, "trip_risk": 2, "status": "Operating Within Thresholds", "dodgy_sensors": []},
        {"index": 87, "anomaly": 0, "trip_risk": 1, "status": "Operating Within Thresholds", "dodgy_sensors": []},
        {"index": 88, "anomaly": 0, "trip_risk": 3, "status": "Operating Within Thresholds", "dodgy_sensors": []},
        {"index": 89, "anomaly": 0, "trip_risk": 1, "status": "Operating Within Thresholds", "dodgy_sensors": []},
        {"index": 90, "anomaly": 0, "trip_risk": 2, "status": "Operating Within Thresholds", "dodgy_sensors": []},
        {"index": 91, "anomaly": 0, "trip_risk": 1, "status": "Operating Within Thresholds", "dodgy_sensors": []},
        {"index": 92, "anomaly": 0, "trip_risk": 2, "status": "Operating Within Thresholds", "dodgy_sensors": []},
        {"index": 93, "anomaly": 0, "trip_risk": 1, "status": "Operating Within Thresholds", "dodgy_sensors": []},
        {"index": 94, "anomaly": 0, "trip_risk": 1, "status": "Operating Within Thresholds", "dodgy_sensors": []},
        {"index": 95, "anomaly": 0, "trip_risk": 2, "status": "Operating Within Thresholds", "dodgy_sensors": []},
        {"index": 96, "anomaly": 0, "trip_risk": 1, "status": "Operating Within Thresholds", "dodgy_sensors": []},
        {"index": 97, "anomaly": 0, "trip_risk": 1, "status": "Operating Within Thresholds", "dodgy_sensors": []},
        {"index": 98, "anomaly": 0, "trip_risk": 2, "status": "Operating Within Thresholds", "dodgy_sensors": []},
        {"index": 99, "anomaly": 0, "trip_risk": 1, "status": "Operating Within Thresholds", "dodgy_sensors": []},
        {"index": 100, "anomaly": 0, "trip_risk": 1, "status": "Operating Within Thresholds", "dodgy_sensors": []}
    ]
}